Workbook

Sheet 候補一覧
A1: 推奨度 | B1: 採用推奨 | C1: チケット# | D1: 工種ID | G1: ドメイン | H1: 題名 | I1: 説明(修正方針の記載元) | J1: パターン分類 | K1: 生成タイプ | L1: 既存カバー状況 | M1: ステータス | N1: データ見込み | O1: チケット種別 | P1: 関連件数 | Q1: 選定理由メモ
A2: ○ | B2: ★ | C2: 605866 | D2: 65-1-32-20637 | E2: 32-1332 | F2: #22 | G2: 一般土木 | H2: 65-1-32-20637 路上路盤再生工 ★子代価の修正･サブルーチン対応後 | I2: h4. 資料 【改定内容_1】P113～116 h4. 資料変更内容 添加剤散布用のﾊﾞｯｸﾎｳ追加 各機械の排ｶﾞｽ基準変更 特殊作業員追加、編成人員変更 日当り施工量変更(養生工有無で切り分け) 諸雑費率変更 混合深さ単位変更 cm→m h4. 修正方針 ※下記DBを読み込みして開始する \\being.group\Being-組織\積算データ課\作業リスト\歩掛変更リスト\R8歩掛変更\999損料\01_v22329_2026.03.XX全国版(損料(R8建設機械等損料表閲覧版))\01_DB 11_【#601126_項目新旧表(名称規格修正・昇格対応)_Copy先修正】20260310DB損料_令和7年度(2025年度).g9so * 代価表 ** ﾊﾞｯｸﾎｳを65-1-32-30307を追加 ** 特殊作業員を追加 ** 諸雑費費の備考欄は修正不要（資料変更された部分は商品状態から記載がないため） ** 諸雑費の対象行変更 * 計算表 ** 特殊作業員の行を追加 ** 計算表S2の計算式 資料通りに修正 ** 日当り施工量の数値を削除（質問No.11に設定し、養生工有無で切り分けできるように） ** ﾊﾞｯｸﾎｳに送る変数を、賃料で計上できるように追加する 規格区分の値を99999に設定し、各数値を送る形にする 労務職種・燃料種類は損料単価より、特殊運転手・ …(続きはチケット参照) | J2: 選択肢追加 / 数値改定 / 単位変更 / 子代価/SC / 質問追加/削除 / 初期値 | K2: 差分型(要旧版確認) | L2: 既存カバー(精度確認用) | M2: Verified | N2: Verified(資料・データ確実) | O2: 修正内容記載チケット | P2: 5 | Q2: 既存カバー領域の精度確認用
A3: ○ | B3: ★ | C3: 613208 | D3: 65-1-32-31089 | E3: 32-4 | F3: #23 | G3: 一般土木 | H3: 65-1-32-31089 輸送費(仮設材)【運用】 / ★SC(65-2-32-23390) | I3: * 資料 ** \\being.group\Being-限定共有\積算基準\02農林\○01農水省・土地改良(土木工事)\○01標準積算基準\2026(R8)\01_改正情報(新旧対比表等)\1．土地改良工事積算基準の改正の概要 「土地改良事業等請負工事積算基準等の運用」新旧対照表（R8.3.27）(PDF 500KB) (index-32).pdf 【運用】2～3/9 * branches ** /歩掛/000001一般土木/branches/version23787_2026.04中旬大規模要望(地域)栃木県歩掛強化【出荷用】 * 修正方針 ** 基本運賃料金を資料通りに修正してください ** 資料通りの地域に適用するように文字修正してください * 単体テスト | J3: 文字修正 / 子代価/SC | K3: 差分型(要旧版確認) | L3: 既存カバー(精度確認用) | M3: Verified | N3: Verified(資料・データ確実) | O3: 修正内容記載チケット | P3: 4 | Q3: 既存カバー領域の精度確認用
A4: ○ | B4: ★ | C4: 608943 | D4: 65-1-32-36990 | E4: 32-1158 | F4: #24 | G4: 一般土木 | H4: 65-1-32-36990 表層（歩道部） 【被災地対応(As工)】 | I4: ■資料ページ 石川県標準単価表 021 --- ■変更内容 被災地サブルーチンの更新、追加 --- ■修正方針 標準単価表が出たので、対象の工種に対して 被災地補正のサブルーチンの反映、追加をしてください --- ■テストケース | J4: 子代価/SC | K4: 差分型(要旧版確認) | L4: 既存カバー(精度確認用) | M4: Verified | N4: Verified(資料・データ確実) | O4: 修正内容記載チケット | P4: 6 | Q4: 既存カバー領域の精度確認用
A5: ○ | B5: ★ | C5: 605704 | D5: 65-1-32-37160 | E5: 32-379 | F5: #25 | G5: 一般土木 | H5: 65-1-32-37160 現場打ち水路（本体） | I5: ■資料ページ P110/336 --- ■変更内容 注釈変更 機械規格名変更 労務入れ替え 材料入れ替え 市場単価削除 --- ■修正方針 J0化 鉄筋材料、市場単価削除 --- ■テストケース | J5: 規格名計上 | K5: 差分型(要旧版確認) | L5: 既存カバー(精度確認用) | M5: Verified | N5: Verified(資料・データ確実) | O5: 修正内容記載チケット | P5: 5 | Q5: 既存カバー領域の精度確認用
A6: ◎ | B6: ★ | C6: 613462 | D6: 65-11-32-20148 | E6: 32-17467 | F6: #26 | G6: NEXCO | H6: 65-11-32-20148 / 65-xxxx-xx-xxxxx NEXCO (令和7年度(2025年度)) - ｺﾝｸﾘｰﾄ舗装版の目地工 (PAV48Y) _ 資材計上の動作見直し | I6: * 修正内容･テストケース http://dev-redmine/issues/487717#歩掛修正 | J6: (個別確認) | K6: 差分型(要旧版確認) | L6: NEW(未カバードメイン) | M6: Closed | N6: Closed(要確認) | O6: 修正内容記載チケット | P6: 1 | Q6: 新ドメイン(65-11)
A7: ◎ | B7: ★ | C7: 605392 | D7: 65-4-32-20028 | E7: 32-20814 | F7: #27 | G7: PC橋 | H7: 65-4-32-20028 横組ｺﾝｸﾘｰﾄ工【SP3】 | I7: * 資料 ** \\being.group\Being-限定共有\積算基準\01一般土木\○02国交省・黄本(土木工事積算基準)\2026(R08)\01_改正情報(新旧対比表等)\2026_02_27公表\国土交通省土木工事・業務の積算基準等の改定 (令和8年2月27日） 【改定内容_2】114,128/144 --- * 拾い出し内容 数値、文字、代価行追加 --- * 修正方針 ** 埋設型枠、埋設型枠端部について *** 埋設型枠は[5-0-766-3460]、埋設型枠端部は[5-0-766-3465]を代価表に置く *** 計上区分を作成する *** 単価DBと単位自動選択の動作を作成する 埋設型枠の場合：「m」なら設計量を聞く／「m」以外なら10m3当り使用数量を聞く 埋設型枠端部の場合：いずれも使用数量を聞く 上記が選択によって適切に代価表に計上されるよう変数や計算式を追加する ** 諸雑費の備考欄を削除（注9､10で型枠に関しての差があるため） ** 資料の表5.4「桁形式」の変更に関する文字を修正 ** 資料の表5.4「編成人員」の数量変更に対応 {{collapse(変更前の修正内容) * 修正内容 ** 代価表 *** 下記で追加された「埋設型枠」、「埋設型枠端部」を追加する ##606254 ⇒ 別タスクにて差し替えを行うため、一旦、下記を2行設 …(続きはチケット参照) | J7: 文字修正 / 選択肢追加 / 規格名計上 / 計上方法変更 / 単価繋ぎ変え / 質問追加/削除 | K7: 差分型(要旧版確認) | L7: NEW(未カバードメイン) | M7: Closed | N7: Closed(要確認) | O7: 修正内容記載チケット | P7: 3 | Q7: 新ドメイン(65-4)
A8: ◎ | B8: ★ | C8: 605395 | D8: 65-4-32-21014 | E8: 32-20834 | F8: #28 | G8: PC橋 | H8: 65-4-32-21014 / 65-4002-50-20553 PC板仮置工【SP3→1】 ※1人テスト | I8: * 資料 ** \\being.group\Being-限定共有\積算基準\01一般土木\○02国交省・黄本(土木工事積算基準)\2026(R08)\01_改正情報(新旧対比表等)\2026_02_27公表\国土交通省土木工事・業務の積算基準等の改定 (令和8年2月27日） 【改定内容_2】122,131/144 --- * 拾い出し内容 ** 機械機種変更、数値変更 --- * 修正内容 ** 計算表 *** 変数S1～S4の数値を資料通りに修正 --- * テストケース ** 選択肢は任意で積算を実行する * 期待結果 ** 各数量は資料通りになっている ** その他は -コピー元の- 商品と一致している | J8: 数値改定 | K8: 差分型(要旧版確認) | L8: NEW(未カバードメイン) | M8: Closed | N8: Closed(要確認) | O8: 修正内容記載チケット | P8: 4 | Q8: 新ドメイン(65-4)
A9: ◎ | B9: ★ | C9: 605396 | D9: 65-4-32-21015 | E9: 32-20835 | F9: #29 | G9: PC橋 | H9: 65-4-32-21015 PC板敷設工【SP3→1】 ※1人テスト | I9: * 資料 ** \\being.group\Being-限定共有\積算基準\01一般土木\○02国交省・黄本(土木工事積算基準)\2026(R08)\01_改正情報(新旧対比表等)\2026_02_27公表\国土交通省土木工事・業務の積算基準等の改定 (令和8年2月27日） 【改定内容_2】122,131/144 --- * 拾い出し内容 ** 機械機種変更、数値変更 --- * 修正内容 ** 計算表 *** S1、S2、S3、S5の数値を資料通りに修正する --- * テストケース ** 選択肢は任意で積算を実行する * 期待結果 ** 各数量は資料通りになっている ** その他は商品と一致している | J9: 数値改定 | K9: 差分型(要旧版確認) | L9: NEW(未カバードメイン) | M9: Closed | N9: Closed(要確認) | O9: 修正内容記載チケット | P9: 4 | Q9: 新ドメイン(65-4)
A10: ◎ | B10: ★ | C10: 606472 | D10: 65-6-32-20632 | E10: 32-10685 | F10: #30 | G10: トンネル | H10: 65-6-32-20632(SC：65-6-32-21117、65-6-32-21121) 型枠工(覆工ｺﾝｸﾘｰﾄ)【SP2】 | I10: ■資料 【改定内容_2】P83/144 【一部改訂_4】P75、76、104/216 --- ■変更内容 質問表が同一になっているため。 本来SCである65-6-32-21117 覆工工 - 型枠工(覆工ｺﾝｸﾘｰﾄ)には数値変更はないが、 実体である65-6-32-20632 型枠工(覆工ｺﾝｸﾘｰﾄ)の数値変更をすることで、影響あるため質問表を分けて修正が必要。 --- ■修正方針 * 計算表 ** 分岐用の変数を作成 * 質問表 ** NO14 分岐用の列を追加、作成した変数を設定してください ** NO2を複写して新規作成 ** 複写で作成した質問表 *** 値は変更後の数値のため修正前の状態へ ** 分岐用の質問表を作成してください *** 計設定で新たに作成した変数を追加 --- ■フロー 分岐用の質問は、X：9 Y：1辺りへ その他は正しい位置へ設定 ※フロー順ソート忘れずに --- ■システムテスト ＜操作＞ ① *SC 65-6-32-21117 型枠工(覆工ｺﾝｸﾘｰﾄ)* から実行 ・「スライドセントルの規格」どちらも選択 ・その他任意で選択 ② *SC 65-6-32-21121 型枠工(覆工ｺﾝｸﾘｰﾄ)* から実行 ・任意で選択 ③ *65-6-32-20632 型枠工(覆工ｺﾝｸﾘｰﾄ)* から実行 ・「スライドセントルの規格 …(続きはチケット参照) | J10: 新規歩掛 / 数値改定 | K10: 差分型(要旧版確認) | L10: NEW(未カバードメイン) | M10: Closed | N10: Closed(要確認) | O10: 修正内容記載チケット | P10: 4 | Q10: 新ドメイン(65-6)
A11: ◎ | B11: ★ | C11: 605652 | D11: 65-6-32-20711 | E11: 32-10735 | F11: #31 | G11: トンネル | H11: 65-6-32-20711 防音扉設置･撤去【SP2】※1人テスト | I11: ■資料 【改定内容_2】P104、105/144 --- ■変更内容 規格、数量、排ガス、(注)1変更 --- ■修正方針 * 質問表 ** NO1 *** 資料通りに数値変更 *** 注釈の追加 | J11: 数値改定 | K11: 差分型(要旧版確認) | L11: NEW(未カバードメイン) | M11: Closed | N11: Closed(要確認) | O11: 修正内容記載チケット | P11: 4 | Q11: 新ドメイン(65-6)
A12: ◎ | B12: ★ | C12: 616195 | D12: 65-9-32-20018 | E12: 32-11291 | F12: #32 | G12: 上水道 | H12: 65-9-32-20018 小口径管布設(人力)据付工 小口径管切断【配管工+α】 ※1人テスト | I12: h2. 【資料頁】 * P29,30 h2. 【変更内容】 * 配管工変更 h2. 【修正方針】 * 配管工の単価は一括置換で作業済のためテストから行う * 配管工の文字は一括置換未対応のため作業から行う * 配管工の割増単価との切替動作は削除する h2. 【配管工変更のテスト】 以下のExcelに記載のテスト観点に従って確認し、修正必要な箇所があれば同時に対応する \\being.group\Being-組織\積算データ課\作業リスト\歩掛変更リスト\R8歩掛変更\09上水道\01_v23747_2026.4月下旬全国版(上水道 R8新旧表)\03_テストケース 【配管工繋ぎ変え】テストケース.xlsx h2. 【テストケース】 |操作|期待結果| |任意で実行|下記以外、動作は商品と一致 配管工は計上されず、特殊作業員の数量は資料通り 配管工割増区分の動作が削除されている| | J12: 単価繋ぎ変え | K12: 差分型(要旧版確認) | L12: NEW(未カバードメイン) | M12: Closed | N12: Closed(要確認) | O12: 修正内容記載チケット | P12: 1 | Q12: 新ドメイン(65-9)
A13: ◎ | B13: ★ | C13: 617097 | D13: 65-9-32-20032 | E13: 32-11310 | F13: #33 | G13: 上水道 | H13: 65-9-32-20032 ﾎﾟﾘｴﾁﾚﾝ管据付工 ※1人テスト | I13: h2. 【資料頁】 * P33 h2. 【変更内容】 * 配管工→特殊作業員へ変更 ※配管工→特殊作業員への変更は下記で対応済み ##616056 ##616036 【配管工繋ぎ変え】テストケース.xlsx より >計算表No.10,11,12 >「特殊作業員又は特殊作業員~」となっています >（元々は「配管工又は特殊作業員」） >⇒設計にまわします h2. 【修正方針】 【計算表】 * 「特殊作業員又は特殊作業員」→「特殊作業員」へ名称修正 h2. 【テストケース】 * 文字修正のみなので単体テストのみでOK | J13: 文字修正 / 単価繋ぎ変え | K13: 差分型(要旧版確認) | L13: NEW(未カバードメイン) | M13: Closed | N13: Closed(要確認) | O13: 修正内容記載チケット | P13: 1 | Q13: 新ドメイン(65-9)
... A37: ◎ | B37: ★ | C37: 612897 | D37: 65-28-32-23 | E37: 32-12279 | F37: #57 | G37: 電気通信 | H37: 65-28-32-23 岩盤清掃【ダム工事積算の解説】※R7、R8年に対応 | I37: +*■資料*+ \\being.group\Being-限定共有\積算基準\28ダム\○01国交省・ダム工事積算\2023(R5)\市販本\ダム工事積算の解説 令和5年度版正誤表(2026.3.12) Upload (202603121323354041).pdf 正誤表 2、4/4 +*■変更点*+ 軽油の数量変更 +*■修正内容*+ 計算表のSKK＝3を1に変更する +*■テスト*+ 実行し、スライム回収機運転の軽油は資料通りになる そのほかは商品と一致する ※R7年度に反映するチケットは別であります | J37: (個別確認) | K37: 差分型(要旧版確認) | L37: NEW(未カバードメイン) | M37: Closed | N37: Closed(要確認) | O37: 修正内容記載チケット | P37: 2 | Q37: 新ドメイン(65-28)
A38: △ | C38: 605398 | D38: 65-4-32-20112 | G38: PC橋 | H38: 65-4-32-20112 機械器具損料【SP1】※1人テスト | I38: * 資料 ** \\being.group\Being-限定共有\積算基準\01一般土木\○02国交省・黄本(土木工事積算基準)\2026(R08)\01_改正情報(新旧対比表等)\2026_02_27公表\国土交通省土木工事・業務の積算基準等の改定 (令和8年2月27日） 【一部改訂_4】170/216 --- * 拾い出し内容 ** 機械機種変更 --- * 修正内容 ** 単価繋ぎ変え PC橋片持架設工用機械器具損料／発動発電機 供用日 2600 [5-0-33-22732] ↓ PC橋片持架設工用機械器具損料／ﾃﾞｨｰｾﾞﾙ45kVA 供用日 0 [5-0-33-103521] ※代価表で変更するだけではすべて繋ぎ変わらないので、チェッカーでの出力結果などを確認して修正すること --- * システムテスト ** 操作 【使用電源】発動発電機 その他は任意で選択 ** 期待結果 繋ぎ変えた単価が計上される 確定後に金額を入力する動作がある --- * 設計メモ {{collapse 資料変更内容としては、発動発電機 規格変更と排ガス変更 Gaiaでは下記の単価で損料を計上している PC橋片持架設工用機械器具損料／発動発電機 供用日 2600 [5-0-33-22732] ⇒ 歩掛側、参考単価にも特に詳しい機械の名称を持っていないため、修正なしと判断 *{c …(続きはチケット参照) | J38: 単価繋ぎ変え | K38: 差分型(要旧版確認) | L38: 制限事項該当の可能性(損料/賃料/運転費系) | M38: Closed | N38: Closed(要確認) | O38: 修正内容記載チケット | P38: 2 | Q38: 新ドメイン(65-4)
A39: △ | C39: 605583 | D39: 65-4-32-20465 | G39: PC橋 | H39: 65-4-32-20465 / 65-XX-XX-XXXXX PC橋 (令和7年度(2025年度)) - ｸﾞﾗｳﾄﾀｲﾌﾟ緊張機器損料(片持架設工法) _ 【供用日数入力方法】の注釈を基準書と一致するように修正する | I39: 修正方針、テストケースは親チケットのエクセル参照 | J39: (個別確認) | K39: 差分型(要旧版確認) | L39: 制限事項該当の可能性(損料/賃料/運転費系) | M39: Closed | N39: Closed(要確認) | O39: 修正内容記載チケット | P39: 1 | Q39: 新ドメイン(65-4)
A40: △ | C40: 605581 | D40: 65-6-32-20057 | G40: トンネル | H40: 65-6-32-20057 濁水処理設備運転【SP1】※#606050、#606049完了後 | I40: ■資料 【改定内容_2】P100、103/144 --- ■変更内容 損料→賃料に変更 加圧脱水機運転追加 --- ■修正方針 【代価表】 ・新規追加した運転費を設定↓ ##606050 ##606049 ・すでに設定されている電力料と損料は削除 【計算表】 ・「(仮)処理能力区分」「(仮)ろ過面積区分」で下位代価へ送る変数として作成 【質問表】 新規作成 ・「(仮)処理能力区分」「(仮)ろ過面積区分」の質問を作成 ※質問No.1を使用してもOKですが規格選択とかが設定されているので注意 ※規格名計上の設定も忘れずに ・「濁水処理装置運転」「加圧脱水機運転」の子代価質問を作成 質問No.2 ・削除 【フロー】 上記の修正に伴ってフローを設定 ※商品から設定されているコマンドは削除 --- ■システムテスト ＜操作＞ ・「(仮)処理能力区分」【】※2パターン実行 ・「(仮)ろ過面積区分」【】※2パターン実行 ＜期待結果＞ ・子代価「濁水処理装置運転」内の質問「(仮)処理能力区分」が親で選択した内容で固定実行される ・子代価「加圧脱水機運転」内の質問「(仮)ろ過面積区分」が親で選択した内容で固定実行される ・規格名計上が適切 | J40: 新規歩掛 / 規格名計上 / 子代価/SC | K40: 差分型(要旧版確認) | L40: 制限事項該当の可能性(損料/賃料/運転費系) | M40: Closed | N40: Closed(要確認) | O40: 修正内容記載チケット | P40: 2 | Q40: 新ドメイン(65-6)
A41: △ | C41: 605641 | D41: 65-6-32-20618 | G41: トンネル | H41: 65-6-32-20618(SC:65-6-32-20913,65-6-32-21059) ずり出し工(ﾀﾞﾝﾌﾟﾄﾗｯｸ運転)【SP2】※#606485完了後、システムテストのみ | I41: ■資料 【改定内容_2】P56～60、88～90、98/144 【一部改訂_4】P48～51、79、80、84、95、109、115/216 --- ■変更内容 規格、数量変更 発破工法、機械掘削工法、小断面トンネル工で燃料消費量変更、機械損料追加 【改定内容_2】P56～60 の数量変更は〇付けチケットで対応済み( #604426 ) --- ■修正方針 運転費の指定事項の修正のみ ※別チケットで対応( #606485 ) このチケットではシステムテストのみしてください --- ■システムテスト ＜操作①＞ 65-6-32-20618 から実行(発破工法) ＜期待結果①＞ ダンプトラックの規格、燃料数量、機械損料数量、タイヤ損耗費の数値が資料通りになっている 上記以外は商品と一致する ＜操作②＞ SC：65-6-32-20913 から実行(機械掘削工法) ＜期待結果②＞ ダンプトラックの規格、燃料数量、機械損料数量、タイヤ損耗費の数値が資料通りになっている 上記以外は商品と一致する ＜操作③＞ SC：65-6-32-21059 から実行(小断面トンネル工) ＜期待結果③＞ ダンプトラックの規格、燃料数量、機械損料数量、タイヤ損耗費の数値が資料通りになっている 上記以外は商品と一致する | J41: (個別確認) | K41: 差分型(要旧版確認) | L41: 制限事項該当の可能性(損料/賃料/運転費系) | M41: Closed | N41: Closed(要確認) | O41: 修正内容記載チケット | P41: 5 | Q41: 新ドメイン(65-6)
A42: △ | C42: 610394 | D42: 65-6-32-20655 | G42: トンネル | H42: 【#608844で対応済み】【詳細設計】65-6-32-20655 給水設備運転【令和8年3月16日訂正資料】 | I42: 3/16公表の訂正資料がきました 水槽の供用日数の数値が変更 下記のチケットで対応済みでした ##608844 このチケットは閉じます --- h2. 設計者 ** 修正内容：実装チケットに記載。 ** 予定工数：実際にかかりそうな時間を入力。 ** タイトル *** 全国工種を修正する場合は地域に合わせて年度毎のチケットが揃っているか確認 *** 【XML】65-xx-xx-xxxxx / 65-xxxx-xx-xxxxx 省庁名 (令和xx年度) - 工種名 _ 修正内容 / ★SC (65-xx-xx-xxxxx) #○○完了後 着手順① *** 【エクセル等】【工種リスト】 省庁名 (令和XX年度) - 工種名 [65-X-32-XXXXX] 計●工種 _ 修正内容 ★～注意事項～ #○○完了後 着手順① ** テストケース：Excelへ記載。 ** ステータス：詳細設計が完了したら、詳細設計タスク・実装タスクを「テストケースレビュー待ち」にしてください --- h2. レビュー者 ** 修正内容：実装チケットを確認。 ** 予定工数：実装チケットの予定工数を確認。 ** テストケース：Excelを確認。 ** ステータス：レビューがOKだった場合、実装タスク「Assign待ち」、詳細設計タスク「Verified」にしてください ** レビューでNGがあった …(続きはチケット参照) | J42: 数値改定 / 子代価/SC | K42: 差分型(要旧版確認) | L42: 制限事項該当の可能性(損料/賃料/運転費系) | M42: Closed | N42: Closed(要確認) | O42: 設計系のみ(修正方針は関連チケット参照) | P42: 1 | Q42: 新ドメイン(65-6)
A43: △ | C43: 606050 | D43: 65-6-32-21479 | G43: トンネル | H43: 新規追加 65-6-32-21479 濁水処理装置運転【SP2】 | I43: ■資料 【改定内容_2】P100、103/144 --- ■変更内容 損料→賃料に変更 加圧脱水機運転追加 上記修正に伴い 濁水処理装置運転の追加が発生 --- ■修正方針 作り方としては「65-1-32-20370」を参考にする 【代価表】 赤本の機-30の表通りに作成 ・電力料は下記を選択 →各種料金 - 水道･光熱費 - 電力料金 - 電力料 - 電力料／低圧臨時 ｋｗｈ 1 [5-0-32-25631] ・濁水処理装置は下記を選択 →ﾘｰｽ(賃貸) - 建設機械賃貸料金 - 濁水処理装置(賃貸) - 濁水処理装置(賃貸)(長期割引あり)／ﾎﾟｰﾀﾌﾞﾙ型･機械処理沈殿方式 30m3/h 台/日 0 [5-0-766-3622] 【計算表】 ・「(仮)処理能力区分」で上位代価から受け取る変数を作成 【質問表】 新規作成 ・65-1-32-20370から質問No.2、No.9、No.3、No.10、No.6をコピー ※名称や数量、規格選択など資料通りになるように適宜修正 ※質問表の「代価数量」は使用しないでください ※計設定も忘れずに ※電力料の動作も65-1-32-20370を参考にする 【フロー】 上記の修正に伴ってフローを設定 --- ■システムテスト ＜操作＞ ・「(仮)処理能力区分」【】※2パターン実行 ・「賃料長期割引の適用」【】※2パターン実行 …(続きはチケット参照) | J43: 新規歩掛 / 単位変更 / 規格名計上 | K43: 全パターン型 | L43: 制限事項該当の可能性(損料/賃料/運転費系) | M43: Closed | N43: Closed(要確認) | O43: 修正内容記載チケット | P43: 1 | Q43: 新ドメイン(65-6)
A44: △ | C44: 606049 | D44: 65-6-32-21480 | G44: トンネル | H44: 新規追加 65-6-32-21480 加圧脱水機運転【SP2】 | I44: ■資料 【改定内容_2】P100、103/144 --- ■変更内容 損料→賃料に変更 加圧脱水機運転追加 上記修正に伴い 濁水処理装置運転の追加が発生 --- ■修正方針 作り方としては「65-1-32-20370」を参考にする 【代価表】 赤本の機-30の表通りに作成 ・電力料は下記を選択 →各種料金 - 水道･光熱費 - 電力料金 - 電力料 - 電力料／低圧臨時 ｋｗｈ 1 [5-0-32-25631] ・加圧脱水機は下記を選択 →ﾘｰｽ(賃貸) - 建設機械賃貸料金 - 加圧脱水機(賃貸) - 加圧脱水機(賃貸)(長期割引あり)／ﾌｨﾙﾀﾌﾟﾚｽ式 ろ過面積19m2 容量250L 台/日 0 [5-0-766-3636] 【計算表】 ・「(仮)ろ過面積区分」で上位代価から受け取る変数を作成 【質問表】 新規作成 ・「(仮)ろ過面積区分」で「19m2」「45m2」の2選択で質問を作成 ・電力料・機械賃料の数量を資料通りに設定 ・65-1-32-20370から質問No.9、No.6をコピー ※質問名や見出しを資料通りに修正 ※電力料の動作も65-1-32-20370を参考 ・「ろ過面積19m2」「ろ過面積45m2」の長期割引あり・なしの質問を作成 ※規格選択も忘れずに ※65-1-32-20370から必要な質問をコピーして加圧脱水機用に変更するのもありかも …(続きはチケット参照) | J44: 新規歩掛 / 単位変更 / 規格名計上 | K44: 全パターン型 | L44: 制限事項該当の可能性(損料/賃料/運転費系) | M44: Closed | N44: Closed(要確認) | O44: 修正内容記載チケット | P44: 1 | Q44: 新ドメイン(65-6)
A45: △ | C45: 609498 | D45: 65-1-32-20156 | G45: 一般土木 | H45: 65-1-32-20156 / 65-1-32-20156 高圧噴射撹拌工(二重管工法)【損料影響確認】#609435完了後 | I45: ■内容 損料が旧損料（【R7】）になるため、新しい損料を使用できるようにする ・旧損料の確認方法 一覧（運転費除く）シート E列：題名の工種MDCDで絞る。 L列：【R7】～ ・新損料の確認方法 旧損料の近辺を探してみてください。 h4. 資料 * 一部改訂_1 P51,52,62,63/172 h4. 修正方針 * 計算表 ** 計算表96行目の値を11→77に変更する h4. テストケース 以下のテストを実行する 変数指定:HK=1を設定し、親[65-1-32-20156]から積算を実行する 操作：積算を実行する 期待結果： * 「高圧噴射攪拌用地盤改良機」の損料規格は「63~77mm」で代価行に計上され、デフォルト位置は正しく設定されている * それ以外の動作･結果は商品と一致する | J45: 初期値 | K45: 差分型(要旧版確認) | L45: 制限事項該当の可能性(損料/賃料/運転費系) | M45: Closed | N45: Closed(要確認) | O45: 修正内容記載チケット | P45: 1 | Q45: 既存カバー領域の精度確認用
A46: △ | C46: 605831 | D46: 65-1-32-20370 | G46: 一般土木 | H46: 65-1-32-20370 濁水処理設備運転 | I46: h4. ■資料 【改定内容_1】P99~101/116 h4. ■修正方針 * 質問 ** 処理区分の質問を作成 ※規格名計上要 ** 質問No2をコピーして常時処理と作業時処理でわける *** 100m3/hの項目は削除して、資料通りの数量に修正 *** 規格区分：FGの列を足す ** 質問No3 *** 100m3/hの項目を削除 * フロー ** コマンドを削除 ** 適切な位置へ配置 h4. ■テストケース * 積算実行 ** 処理区分：全パターン ** 処理能力：全パターン * 期待結果 ** 資料通りの数量が計上される ** 適切に規格名計上されている | J46: 規格名計上 | K46: 差分型(要旧版確認) | L46: 制限事項該当の可能性(損料/賃料/運転費系) | M46: Closed | N46: Closed(要確認) | O46: 修正内容記載チケット | P46: 2 | Q46: 既存カバー領域の精度確認用
A47: △ | C47: 609086 | D47: 65-1-32-24192 | G47: 一般土木 | H47: 【赤本対応時作業】65-1-32-24192 H形鋼打込工(ﾌﾟﾚﾎﾞｰﾘﾝｸﾞ) 【損料影響確認】 | I47: ■内容 損料が旧損料（【R7】）になるため、新しい損料を使用できるようにする ・旧損料の確認方法 一覧（運転費除く）シート E列：題名の工種MDCDで絞る。 L列：【R7】～ ・新損料の確認方法 旧損料の近辺を探してみてください。 | J47: (個別確認) | K47: 差分型(要旧版確認) | L47: 制限事項該当の可能性(損料/賃料/運転費系) | M47: Closed | N47: Closed(要確認) | O47: 修正内容記載チケット | P47: 1 | Q47: 既存カバー領域の精度確認用
A48: △ | C48: 609087 | D48: 65-1-32-26078 | G48: 一般土木 | H48: 65-1-32-26078 間接費(回航･えい航費)(引船) 【損料影響確認】ｸﾚｰﾝ付台船 | I48: ■内容 損料が旧損料（【R7】）になるため、新しい損料を使用できるようにする ・旧損料の確認方法 一覧（運転費除く）シート E列：題名の工種MDCDで絞る。 L列：【R7】～ ・新損料の確認方法 旧損料の近辺を探してみてください。 ※ｸﾚｰﾝ付台船について補足 元々「クローラクレーン + 台船」と2行に別れていたものが1行に統合されてきました。 損料データは、既存規格を旧処理し、規格の追加を行います。 歩掛側でも、2行計上→1行計上への変更が必要になります。 ■修正内容 * 代価表 ** 代価行5行目を[6-0-33-8197]に繋ぎ変える ※金額は供用1日当り損料(11欄)で一括置換する ** 代価行6行目を削除する * 質問表 ** 質問No.6 *** 「ｸﾚｰﾝ規格」→「ｸﾚｰﾝ付台船規格」に質問名、列名称を変更する *** 選択肢1行目[6-0-33-8197] 選択肢2行目[6-0-33-8198] 選択肢3行目[6-0-33-8199]に繋ぎ変える ** 質問No.7を削除する ※フローを修正する ■テストケース * 操作1 「ﾌﾞﾛｯｸ実質量」【4.5t以下】 * 期待結果1 ｸﾚｰﾝ付台船は代価行1行で計上され、損料規格は「45~50t吊」になっている 上記以外の動作、結果は商品と一致する * 操作2 再選択 「ﾌﾞﾛｯｸ実質量」【4.5tを超え7.5t …(続きはチケット参照) | J48: 選択肢追加 / 単価繋ぎ変え / 質問追加/削除 | K48: 差分型(要旧版確認) | L48: 制限事項該当の可能性(損料/賃料/運転費系) | M48: Closed | N48: Closed(要確認) | O48: 修正内容記載チケット | P48: 1 | Q48: 既存カバー領域の精度確認用
A49: △ | C49: 609088 | D49: 65-1-32-26079 | G49: 一般土木 | H49: 65-1-32-26079 / 65-4002-50-22513 間接費(回航用艤装費) 【損料影響確認】ｸﾚｰﾝ付台船 | I49: ■内容 損料が旧損料（【R7】）になるため、新しい損料を使用できるようにする ・旧損料の確認方法 一覧（運転費除く）シート E列：題名の工種MDCDで絞る。 L列：【R7】～ ・新損料の確認方法 旧損料の近辺を探してみてください。 ※ｸﾚｰﾝ付台船について補足 元々「クローラクレーン + 台船」と2行に別れていたものが1行に統合されてきました。 損料データは、既存規格を旧処理し、規格の追加を行います。 歩掛側でも、2行計上→1行計上への変更が必要になります。 ■修正内容 ※コピー元[65-4002-50-22513]から修正開始、修正後[65-1-32-26079]にコンバートする * 代価表 ** 代価行3行目を削除する * 質問表 ** 質問No.8 *** セット変数DAの列名称を「台船規格」に、台船200t積以外の行の値を【0】に変更する *** セット変数KUの列名称を「ｸﾚｰﾝ付台船規格」に変更する *** ｸﾚｰﾝ付台船の規格の「･○○○t積」を削除して、規格名計上を修正する *** 選択肢4行目を削除、計設定を修正する ** 質問No.6 *** 「ｸﾚｰﾝ付台船(ｸﾛｰﾗｸﾚｰﾝ)規格」→「ｸﾚｰﾝ付台船規格」に質問名、列名称を変更する *** 選択肢1行目[6-0-33-8197] 選択肢2行目[6-0-33-8198] 選択肢3行目[6-0-33-819 …(続きはチケット参照) | J49: 選択肢追加 / 選択肢削除 / 規格名計上 / 単価繋ぎ変え / 質問追加/削除 | K49: 差分型(要旧版確認) | L49: 制限事項該当の可能性(損料/賃料/運転費系) | M49: Closed | N49: Closed(要確認) | O49: 修正内容記載チケット | P49: 1 | Q49: 既存カバー領域の精度確認用
... A132: △ | C132: 603871 | D132: 65-3-32-20565 | G132: 港湾 | H132: 65-3-32-20565 港湾 (令和7年度(2025年度)) - 捨石均し船 運転 ☆作業船☆ ※一人テスト | I132: h4. *■修正方針■* ##603332 を参照してください h4. *■テストケース■* 単体テストで以下を確認 * 代価表 トランスポンダが追加。式は ##603332 と同じ * 計算表 サブルーチン以外の差分なし * 質問表 サブルーチン以外の差分なし * フロー 最後にICTの質問が増えている 以外の差分なし | J132: 子代価/SC | K132: 差分型(要旧版確認) | L132: 制限事項該当の可能性(損料/賃料/運転費系) | M132: Closed | N132: Closed(要確認) | O132: 修正内容記載チケット | P132: 2 | Q132: 新ドメイン(65-3)。Verified豊富(運転費系除外)
A133: △ | C133: 604343 | D133: 65-3-32-21653 | G133: 港湾 | H133: 65-3-32-21653 港湾 (令和7年度(2025年度)) - 起重機船(非航旋回) 運転 【海岸関連】 | J133: (個別確認) | K133: 差分型(要旧版確認) | L133: 制限事項該当の可能性(損料/賃料/運転費系) | M133: Closed | N133: Closed(要確認) | O133: 修正内容記載チケット | P133: 2 | Q133: 新ドメイン(65-3)。Verified豊富(運転費系除外)
A134: △ | C134: 604344 | D134: 65-3-32-21656 | G134: 港湾 | H134: 65-3-32-21656 港湾 (令和7年度(2025年度)) - 潜水士船 運転 【海岸関連】 | J134: (個別確認) | K134: 差分型(要旧版確認) | L134: 制限事項該当の可能性(損料/賃料/運転費系) | M134: Closed | N134: Closed(要確認) | O134: 修正内容記載チケット | P134: 2 | Q134: 新ドメイン(65-3)。Verified豊富(運転費系除外)
A135: △ | C135: 609332 | D135: 65-25-32-986 | G135: 空港 | H135: 65-25-32-986 散水車運転 単価の繋ぎ変え 【R8.4改廃影響】 | I135: h4. *■背景■* https://being-gaia-kaihatsu.slack.com/archives/CFT2P3JQN/p1773906560577099 R8.4 市販単価にて賃料が登録された これが、もともと歩掛で計上されていた単価とは別。 金額が計上できるように歩掛で計上する単価を繋ぎ変える h4. *■対応すること■* リース(賃貸) - 建設機械賃貸料金 - 散水車(賃貸) - 散水車 トラック架装型・3800L 日 0 [32-1-102-33-192889] [5-0-33-192889] ↓ リース(賃貸) - 建設機械賃貸料金 - 散水車(賃貸) - 道路維持用機械 散水車(賃貸)(長期割引あり) トラック架装型 3800L 台/日 [32-3-102-766-3642] [5-0-766-3642] リース(賃貸) - 建設機械賃貸料金 - 散水車(賃貸) - 道路維持用機械 散水車(賃貸)(長期割引なし) トラック架装型 3800L 台/日 [32-3-102-766-3643] [5-0-766-3643] につなぎ変える %{color:red}長期割引の動作にも対応する% h4. *■システムテスト■* * 最新の市販単価（R8.4）のある状態で実行 ** 長期割引あり、なしを切り替え →金額が計上できている | J135: 単価繋ぎ変え | K135: 差分型(要旧版確認) | L135: 制限事項該当の可能性(損料/賃料/運転費系) | M135: Verified | N135: Verified(資料・データ確実) | O135: 修正内容記載チケット | P135: 1 | Q135: 新ドメイン(65-25)
A136: △ | C136: 612801 | D136: 65-2-32-23138 | G136: 農林 | H136: 65-2-32-23138 / 65-4002-50-22513 回航用艤装費【河川･水路工】 / ★SC(65-2-32-25634) 【旧損料】 | I136: ■変更内容 損料変更 h4. *■外部設計■* 一般土木 #609088 での修正を農林に反映済みのためテストのみ必要 h4. *■内部設計■* コンバートのみ h4. *■テストケース■* * 積算実行【1】 操作1 「作業船の選択」【35~40t吊】 期待結果1 ｸﾚｰﾝ付台船は代価行1行で計上され、損料規格は「35~40t吊」になっている 「作業船の選択」の規格で「45~50t吊」を含む選択肢は1つで、ｸﾚｰﾝ付台船の規格から「･○○○t積」は削除されている 規格名計上は正しく計上される 上記以外の動作、結果は商品と一致する 操作2 再選択 「作業船の選択」【45~50t吊】 期待結果2 ｸﾚｰﾝ付台船は代価行1行で計上され、損料規格は「45~50t吊」になっている 規格名計上は正しく計上される 上記以外の動作、結果は商品と一致する 操作3 再選択 「作業船の選択」【80t吊】 期待結果3 ｸﾚｰﾝ付台船は代価行1行で計上され、損料規格は「80t吊」になっている 規格名計上は正しく計上される 上記以外の動作、結果は商品と一致する 操作4 再選択 「作業船の選択」【100t吊】 期待結果4 ｸﾚｰﾝ付台船は代価行1行で計上され、損料規格は「100t吊」になっている 規格名計上は正しく計上される 上記以外の動作、結果は商品と一致する 操作5 「作業船の選択」【150t …(続きはチケット参照) | J136: 規格名計上 / 子代価/SC | K136: 差分型(要旧版確認) | L136: 制限事項該当の可能性(損料/賃料/運転費系) | M136: Verified | N136: Verified(資料・データ確実) | O136: 修正内容記載チケット | P136: 2 | Q136: 新ドメイン(65-2)
A137: △ | C137: 612808 | D137: 65-2-32-23352 | G137: 農林 | H137: 65-2-32-23352 / 65-4002-50-22513 回航用艤装費【仮設工】 / ★SC(65-2-32-26176) 【旧損料】 | I137: ■変更内容 損料変更 h4. *■外部設計■* 一般土木 #609085 での修正を農林に反映済みのためテストのみ必要 h4. *■内部設計■* コンバートのみ h4. *■テストケース■* * 積算実行【1】 操作1 「作業船の選択」【35~40t吊】 期待結果1 ｸﾚｰﾝ付台船は代価行1行で計上され、損料規格は「35~40t吊」になっている 「作業船の選択」の規格で「45~50t吊」を含む選択肢は1つで、ｸﾚｰﾝ付台船の規格から「･○○○t積」は削除されている 規格名計上は正しく計上される 上記以外の動作、結果は商品と一致する 操作2 再選択 「作業船の選択」【45~50t吊】 期待結果2 ｸﾚｰﾝ付台船は代価行1行で計上され、損料規格は「45~50t吊」になっている 規格名計上は正しく計上される 上記以外の動作、結果は商品と一致する 操作3 再選択 「作業船の選択」【80t吊】 期待結果3 ｸﾚｰﾝ付台船は代価行1行で計上され、損料規格は「80t吊」になっている 規格名計上は正しく計上される 上記以外の動作、結果は商品と一致する 操作4 再選択 「作業船の選択」【100t吊】 期待結果4 ｸﾚｰﾝ付台船は代価行1行で計上され、損料規格は「100t吊」になっている 規格名計上は正しく計上される 上記以外の動作、結果は商品と一致する 操作5 「作業船の選択」【150t …(続きはチケット参照) | J137: 規格名計上 / 子代価/SC | K137: 差分型(要旧版確認) | L137: 制限事項該当の可能性(損料/賃料/運転費系) | M137: Verified | N137: Verified(資料・データ確実) | O137: 修正内容記載チケット | P137: 2 | Q137: 新ドメイン(65-2)
A138: △ | C138: 613433 | D138: 65-2-32-23568 | G138: 農林 | H138: 65-2-32-23568 / 65-4002-50-24197 空気圧縮機運転(可搬式)【機械単価表】 / ★SC(65-2-32-26742) | I138: ■資料 【標準歩掛】39/162 ■変更内容 h4. *■外部設計■* 規格変更 一般土木と同じ変更内容を反映する h4. *■内部設計■* * 質問 ** No62の内容を存在する工種のみNo61と同じ内容になるように変更する ** No68の内容を存在する工種のみNo67と同じ内容になるように変更する ** No74の内容を存在する工種のみNo73と同じ内容になるように変更する h4. *■テストケース■* 資料と同じか確認 | J138: 子代価/SC | K138: 差分型(要旧版確認) | L138: 制限事項該当の可能性(損料/賃料/運転費系) | M138: Verified | N138: Verified(資料・データ確実) | O138: 修正内容記載チケット | P138: 2 | Q138: 新ドメイン(65-2)
A139: △ | C139: 602024 | D139: 65-2-32-23230 | G139: 農林 | H139: 65-2-32-23230 / 65-4002-50-24417 農林 (令和7年度(2025年度)) - PC橋桁機械器具損料 _ コピー元を配っても問題が起きないようにコピー元に対して修正を行う ＜配るのみ（要確認）＞ | I139: h4. *■修正方針* [65-4002-50-24417]を[65-2-32-23230]にコンバートする h4. *■テストケース* 操作 積算を実行[65-2-32-23230] 期待結果 動作と結果は商品と一致する --- h4. *■目的* 現在該当工種はコピー先≠コピー元の状態であり、配ることで差分がでる R8改定以降で改定があった際にコピー元を配るだけ で完了するようにしたい ①一般土木で改定済み（コピー元で改定済み）を農林に配る ②農林（コピー元で改定済み）を治山林道といった他省庁に配る コピー先のみで修正されている農林の独自動作があれば、コピー元に組み込む 結果として、配ったあとの農林 及び 他省庁の挙動が変わらない ことをテストする h4. *■一人目調査内容* 有(配布可)?★ 一部農林に影響のある差分あり ・供用日数算出方法の有無 ・ﾌﾛｰ分岐用の省庁区分の有無 ・ｹｰﾌﾞﾙ規格の選択肢の増減 →ｺﾋﾟｰ元、ｺﾋﾟｰ先のｹｰﾌﾞﾙ規格が資料と不一致(選択肢が資料より多い) h4. *■前田確認時メモ* * *供用日数算出方法* ・商品 なし 計算かつ省庁区分SFK2で発注者丸めの値を採用で固定 ・配布後 !2026-02-17_09h32_39.png! 計算か直入の選択はあるが、計算デフォ実行なので問題なし 計算後の丸めも、省庁区分S …(続きはチケット参照) | J139: (個別確認) | K139: 差分型(要旧版確認) | L139: 制限事項該当の可能性(損料/賃料/運転費系) | M139: Closed | N139: Closed(要確認) | O139: 修正内容記載チケット | P139: 2 | Q139: 新ドメイン(65-2)
A140: △ | C140: 612806 | D140: 65-2-32-23434 | G140: 農林 | H140: 65-2-32-23434 / 65-4002-50-23963 高圧噴射撹拌用地盤改良機【機械単価表】 / ★SC(65-2-32-26466) 【旧損料】※テストのみ | I140: h4. 資料 * 【標準歩掛】 P43～44/162 * 【一部改訂_1】 P62～64/172 h4. 修正方針 * 親工種からテストのみ実行する h4. テストケース 以下のテストを実行する 手順1 操作：[65-2-32-23099]で変数指定HK=1を行ったうえで積算を実行する 期待結果： * 「高圧噴射攪拌用地盤改良機」の損料規格は「63~77mm」で代価行に計上され、デフォルト位置は正しく設定されている * 上記以外の動作･結果は商品と一致する 手順2 操作：[65-2-32-25558]で変数指定HK=1を行ったうえで積算を実行する 期待結果： * 「高圧噴射攪拌用地盤改良機」の損料規格は「63~77mm」で代価行に計上され、デフォルト位置は正しく設定されている * 上記以外の動作･結果は商品と一致する | J140: 子代価/SC / 初期値 | K140: 差分型(要旧版確認) | L140: 制限事項該当の可能性(損料/賃料/運転費系) | M140: Closed | N140: Closed(要確認) | O140: 修正内容記載チケット | P140: 2 | Q140: 新ドメイン(65-2)
A141: △ | C141: 606733 | D141: 65-2-32-23479 | G141: 農林 | H141: 65-2-32-23479 / 65-4002-50-24021 農林 (令和7年度(2025年度)) - 発動発電機 _ 賃料の燃料消費率を修正 /★#606732完了後着手：XML反映のみ | I141: ■修正方法＆テストケース https://dev-redmine.being.group/issues/595219#note-28 | J141: (個別確認) | K141: 差分型(要旧版確認) | L141: 制限事項該当の可能性(損料/賃料/運転費系) | M141: Closed | N141: Closed(要確認) | O141: 修正内容記載チケット | P141: 1 | Q141: 新ドメイン(65-2)
A142: △ | C142: 613429 | D142: 65-2-32-23561 | G142: 農林 | H142: 65-2-32-23561 / 65-4002-50-24190 ｱｽﾌｧﾙﾄﾌｨﾆｯｼｬ【機械単価表】 / ★SC(65-2-32-26732) 【旧損料】 | J142: 子代価/SC | K142: 差分型(要旧版確認) | L142: 制限事項該当の可能性(損料/賃料/運転費系) | M142: Closed | N142: Closed(要確認) | O142: 修正内容記載チケット | P142: 2 | Q142: 新ドメイン(65-2)
A143: △ | C143: 612935 | D143: 65-28-32-248 | G143: 電気通信 | H143: 65-28-32-248 中央ﾌﾟﾗﾝﾄ運転費 | I143: +*■資料*+ \\being.group\Being-限定共有\積算基準\28ダム\○01国交省・ダム工事積算\2026(R8)\令和７年度改定箇所（令和８年４月１日以降適用） (001982681).pdf 新旧表 33/39 ※2～3/39 は第2弾で対応 +*■変更点*+ 労務数量変更 +*■修正内容*+ ・代価表の労務の数量を変数にする 計算表に資料通りの値を設定する（中央プラント） ・計算表 5行目を4.5に変更 ※メモがR3ダムの解説の内容になっている 今回はダム工事積算資料の新旧表対応なので解説の内容はそのままとする +*■テスト*+ 任意の条件で実行し ・労務数量は資料と一致する ・そのほかは商品と一致する | J143: (個別確認) | K143: 差分型(要旧版確認) | L143: 制限事項該当の可能性(損料/賃料/運転費系) | M143: Closed | N143: Closed(要確認) | O143: 修正内容記載チケット | P143: 1 | Q143: 新ドメイン(65-28)
A144: △ | C144: 612907 | D144: 65-28-32-40 | G144: 電気通信 | H144: 65-28-32-40 二次･三次破砕設備運転 ※1人テスト | I144: +*■資料*+ \\being.group\Being-限定共有\積算基準\28ダム\○01国交省・ダム工事積算\2026(R8)\令和７年度改定箇所（令和８年４月１日以降適用） (001982681).pdf 新旧表 15/39 +*■変更点*+ 労務数量変更 +*■修正内容*+ ・質問No11を資料通りに修正 +*■テスト*+ 単体テストのみでOK | J144: (個別確認) | K144: 差分型(要旧版確認) | L144: 制限事項該当の可能性(損料/賃料/運転費系) | M144: Closed | N144: Closed(要確認) | O144: 修正内容記載チケット | P144: 1 | Q144: 新ドメイン(65-28)
A145: △ | C145: 612909 | D145: 65-28-32-42 | G145: 電気通信 | H145: 65-28-32-42 骨材貯蔵･運搬設備運転 ※1人テスト | I145: +*■資料*+ \\being.group\Being-限定共有\積算基準\28ダム\○01国交省・ダム工事積算\2026(R8)\令和７年度改定箇所（令和８年４月１日以降適用） (001982681).pdf 新旧表 15/39 +*■変更点*+ 労務数量変更 +*■修正内容*+ 労務だけでも代価表を変数にして計算表に値を持たせる +*■テスト*+ 任意の条件で実行 ・労務の数量は資料通りになる ・そのほかは商品と一致する | J145: (個別確認) | K145: 差分型(要旧版確認) | L145: 制限事項該当の可能性(損料/賃料/運転費系) | M145: Closed | N145: Closed(要確認) | O145: 修正内容記載チケット | P145: 1 | Q145: 新ドメイン(65-28)
A146: ○ | C146: 605673 | D146: 65-1-32-36938 | G146: 一般土木 | H146: 65-1-32-36938 掘削 【A】 | I146: ■資料ページ P1、2、4～/336 --- ■変更内容 適用変更 大幅変更 --- ■修正方針 LowN の変数は現在使用されてないことを確認したので削除します。 ※影響のある質問なども含めて （発注者マスタ、変数指定、送り変数） L_Noiは #81917 の対応で栃木県で使用されていますが、 栃木県の最新の資料上からは選択が消えているのを確認出来たので、こちらも削除 \\being.group\Being-限定共有\地域情報・作成依頼・設計書\資料一覧(★7)\歩掛\09栃木県\栃木県\県土整備部\令和7年\01_R7_共通編.pdf jsk の変数は旧工種からしか使用されてないので削除します。 ※影響のある質問なども含めて J●の初期化ですが、どの質問を通る時にどの変数を初期化と判断するのが手間+メンテ時も影響確認が大変になるため J3以降の質問については自分以降のJ●を初期化するようにします。 ※J1は必ずJ2の質問を通るためJ2の質問以降で設定します。 J4の質問など同じ選択で以降の質問を固定化させるために質問分けてましたが これはやめて、分岐後に固定の質問を追加する形に変更します。 質問58,59,60で機械の計上のON･OFFを設定してますが 計設定と計上の関係を都度考えるのが大変なので、 ほぼ全行(土砂と岩塊･玉石は共通)のパターンを作成して必要 …(続きはチケット参照) | J146: 子代価/SC / 質問追加/削除 | K146: 差分型(要旧版確認) | L146: 既存カバー(精度確認用) | M146: Verified | N146: Verified(資料・データ確実) | O146: 修正内容記載チケット | P146: 3 | Q146: 既存カバー領域の精度確認用
A147: ○ | C147: 605669 | D147: 65-1-32-36939 | G147: 一般土木 | H147: 65-1-32-36939 土砂等運搬 | I147: ■資料ページ P15～/336 --- ■変更内容 条件変更 機械規格名変更 --- ■修正方針 質問No2,12の名称変更 上記に合わせて規格名が被った部分を変更 --- ■テストケース | J147: 文字修正 / 規格名計上 | K147: 差分型(要旧版確認) | L147: 既存カバー(精度確認用) | M147: Verified | N147: Verified(資料・データ確実) | O147: 修正内容記載チケット | P147: 1 | Q147: 既存カバー領域の精度確認用
A148: ○ | C148: 608928 | D148: 65-1-32-36940 | G148: 一般土木 | H148: 65-1-32-36940 整地 【被災地対応】 | I148: ■資料ページ 石川県標準単価表 002 --- ■変更内容 被災地サブルーチンの更新、追加 --- ■修正方針 標準単価表が出たので、対象の工種に対して 被災地補正のサブルーチンの反映、追加をしてください --- ■テストケース | J148: 子代価/SC | K148: 差分型(要旧版確認) | L148: 既存カバー(精度確認用) | M148: Verified | N148: Verified(資料・データ確実) | O148: 修正内容記載チケット | P148: 2 | Q148: 既存カバー領域の精度確認用
A149: ○ | C149: 608933 | D149: 65-1-32-36941 | G149: 一般土木 | H149: 65-1-32-36941 路体（築堤）盛土 【被災地対応】 | I149: ■資料ページ 石川県標準単価表 003 --- ■変更内容 被災地サブルーチンの更新、追加 --- ■修正方針 標準単価表が出たので、対象の工種に対して 被災地補正のサブルーチンの反映、追加をしてください --- ■テストケース | J149: 子代価/SC | K149: 差分型(要旧版確認) | L149: 既存カバー(精度確認用) | M149: Verified | N149: Verified(資料・データ確実) | O149: 修正内容記載チケット | P149: 1 | Q149: 既存カバー領域の精度確認用
A150: ○ | C150: 608932 | D150: 65-1-32-36942 | G150: 一般土木 | H150: 65-1-32-36942 路床盛土 【被災地対応】 | I150: ■資料ページ 石川県標準単価表 004 --- ■変更内容 被災地サブルーチンの更新、追加 --- ■修正方針 標準単価表が出たので、対象の工種に対して 被災地補正のサブルーチンの反映、追加をしてください --- ■テストケース | J150: 子代価/SC | K150: 差分型(要旧版確認) | L150: 既存カバー(精度確認用) | M150: Verified | N150: Verified(資料・データ確実) | O150: 修正内容記載チケット | P150: 1 | Q150: 既存カバー領域の精度確認用
A151: ○ | C151: 605675 | D151: 65-1-32-36943 | G151: 一般土木 | H151: 65-1-32-36943 押土（ルーズ） | I151: ■資料ページ P21/336 --- ■変更内容 条件変更 機械規格名変更 排ガス変更 --- ■修正方針 施工数量追加 排ｶﾞｽ質問差替+追加 --- ■テストケース | J151: 規格名計上 / 質問追加/削除 | K151: 差分型(要旧版確認) | L151: 既存カバー(精度確認用) | M151: Verified | N151: Verified(資料・データ確実) | O151: 修正内容記載チケット | P151: 1 | Q151: 既存カバー領域の精度確認用
A152: ○ | C152: 605676 | D152: 65-1-32-36944 | G152: 一般土木 | H152: 65-1-32-36944 積込（ルーズ） | I152: ■資料ページ P22/336 --- ■変更内容 機械規格名変更 排ガス変更 --- ■修正方針 LowNは現状使用してないことを確認したので削除 (マスタ、変数指定、送り変数) L_Noiは #81917 の対応で栃木県で使用されていますが、 栃木県の最新の資料上からは選択が消えているのを確認出来たので、こちらも削除 \\being.group\Being-限定共有\地域情報・作成依頼・設計書\資料一覧(★7)\歩掛\09栃木県\栃木県\県土整備部\令和7年\01_R7_共通編.pdf P373-374/1102 排ｶﾞｽの質問を差し替え --- ■テストケース | J152: 規格名計上 / 子代価/SC | K152: 差分型(要旧版確認) | L152: 既存カバー(精度確認用) | M152: Verified | N152: Verified(資料・データ確実) | O152: 修正内容記載チケット | P152: 2 | Q152: 既存カバー領域の精度確認用
A153: ○ | C153: 605722 | D153: 65-1-32-36947 | G153: 一般土木 | H153: 65-1-32-36947 安定処理 | I153: ■資料ページ P36～/336 --- ■変更内容 適用変更 条件追加 機械規格名変更 労務入れ替え --- ■修正方針 固化材区分の追加、固化材の材料以上の子代価も存在しているため 親子共々修正が必要。 予想では標準単価表の固化材の分母単価自体は固定だと思うのでJ6=1になるのでは？ と思っている。 --- ■テストケース | J153: 規格名計上 / 子代価/SC | K153: 差分型(要旧版確認) | L153: 既存カバー(精度確認用) | M153: Verified | N153: Verified(資料・データ確実) | O153: 修正内容記載チケット | P153: 2 | Q153: 既存カバー領域の精度確認用
A154: ○ | C154: 605721 | D154: 65-1-32-36955 | G154: 一般土木 | H154: 65-1-32-36955 重力式擁壁 | I154: ■資料ページ P72～/336 --- ■変更内容 条件変更 機械規格名変更 労務変更 --- ■修正方針 擁壁平均高さが2m未満の場合は圧送管延長の質問が不要になった。 質問No1でJ6を初期化し、2m未満の場合は、養生の後に質問を通らないように変更。 J0化する J2=1 J5=3と4が入れ替えになると思われる。 --- ■テストケース | J154: 規格名計上 | K154: 差分型(要旧版確認) | L154: 既存カバー(精度確認用) | M154: Verified | N154: Verified(資料・データ確実) | O154: 修正内容記載チケット | P154: 1 | Q154: 既存カバー領域の精度確認用
... A892: ◎ | C892: 611925 | D892: 65-3-32-24452 | G892: 港湾 | H892: 65-3-32-24452 えい航費【参考】 【回航費･えい航費】 | I892: h4. 資料ページ (3/24差替え)86～86/129 (3/30差替え)86～86/129 h4. 変更内容 被えい航船舶に変更有 土運船の回航においての追記あり 起重機船(非航固定)の規格変更 h4. 修正方針 * 作業船の選択とえい航用引船と被えい航船舶の組合せ表(R7一式版P5-1-16)が一致していないので情報を残す ** 削除された動作は参考と明記する ** 組合せ表と違う場所に記載されているものはメモに資料ページを残す ** 要望で追加された動作はチケット番号を残す * 土運船･台船2隻引の別途考慮 ** 資料に合わせて「1隻引」の文字を削除(要望で追加した質問も同様) ** 2隻引の動作は参考として残す(要望で追加した質問も同様) ** 質問の注釈に明記する * 非航固定起重機船規格追加 ** 損料追加済み ** 規格選択の質問はDH式で他と異なるので一番下に追加 ** 引船規格は組合せ表の注釈通り * 潜水士船の規格変更 ** 損料追加済み ** 旧になった規格は残して追加する ** 初期値をD320PS型に設定 * その他 ** 土運船の質問のメモに「開閉式」「密閉式」を追記 h4. テストケース \\being.group\Being-組織\積算データ課\作業リスト\歩掛変更リスト\R8歩掛変更\03港湾\01_v23534_2026 …(続きはチケット参照) | J892: 選択肢追加 / 初期値 | K892: 差分型(要旧版確認) | L892: NEW(未カバードメイン) | M892: Verified | N892: Verified(資料・データ確実) | O892: 修正内容記載チケット | P892: 2 | Q892: 新ドメイン(65-3)。Verified豊富(運転費系除外)
A893: ◎ | C893: 603964 | D893: 65-3-32-21647 | G893: 港湾 | H893: 65-3-32-21647 / 65-4002-50-22450 捨石本均し･捨石荒均し(海岸) ☆親工種☆ | J893: (個別確認) | K893: 差分型(要旧版確認) | L893: NEW(未カバードメイン) | M893: Closed | N893: Closed(要確認) | O893: 修正内容記載チケット | P893: 1 | Q893: 新ドメイン(65-3)。Verified豊富(運転費系除外)
A894: ◎ | C894: 603953 | D894: 65-3-32-21651 | G894: 港湾 | H894: 65-3-32-21651 / 65-4002-50-20836 消波ﾌﾞﾛｯｸ据付(海岸) ☆親工種☆ | J894: (個別確認) | K894: 差分型(要旧版確認) | L894: NEW(未カバードメイン) | M894: Closed | N894: Closed(要確認) | O894: 修正内容記載チケット | P894: 1 | Q894: 新ドメイン(65-3)。Verified豊富(運転費系除外)
A895: ◎ | C895: 612679 | D895: 65-3-32-24457 | G895: 港湾 | H895: 65-3-32-24457 ｹｰｿﾝえい航【参考】 | I895: h4. 資料ページ 16/129 h4. 変更内容 潜水士船規格変更 h4. 修正方針 質問No86に320を追加する（旧規格は残すと質問No88にあり） 【確認】 こちらの工種ですが、省庁区分「ｹｰｿﾝ曳航費」SFK1=1 計設定SF=10.1 のため、質問No.78｢工種区分｣【ｹｰｿﾝ曳航費】になり、質問No.86「潜水士船の選択」はとおりません。 修正しますか？ 以下の工種も「潜水士船の選択」はありますが、省庁区分の設定でとおりません。 65-3-32-24456 ｹｰｿﾝ回航【参考】 65-3-32-21568 ｹｰｿﾝ回航:運転費【参考】 h4. テストケース | J895: (個別確認) | K895: 差分型(要旧版確認) | L895: NEW(未カバードメイン) | M895: Closed | N895: Closed(要確認) | O895: 修正内容記載チケット | P895: 2 | Q895: 新ドメイン(65-3)。Verified豊富(運転費系除外)
A896: ◎ | C896: 604351 | D896: 65-3-32-26612 | G896: 港湾 | H896: 65-3-32-26612 港湾 (令和7年度(2025年度)) - ﾄﾗﾝｽﾎﾟﾝﾀﾞ艤装ﾃｽﾄ【新規追加】 | I896: h4. *■資料■* ICT を活用した工事安全対策試行工事（潜水作業） 積算要領（令和７年度） (001880123).pdf 新規作成 h4. *■外部設計■* * 潜水士船 「②ダイバーカメラ」「③水中同時通話装置」は 発注者が選定し、契約後に受発注者で協議により実施 のため計上区分をつける ※ この工種はICT安全対策の工種なので、ボンベは計上固定とします。 ※ 艤装テストでは実際に潜水士が水中に入り、位置精度の確認作業を行うため、安全確保のためのボンベは必須となります 。 また、そのほかのICT安全対策機器を計上するかどうか？を選択するのが望ましいです * 起重機船 ** *艤装の目的* ： トランスポンダは「作業船オペレータ」が潜水士の位置を把握するための機器であり、実際に作業を行う船に取り付ける必要があるためです 。 %{color:red}この親代価内に「トランスポンダ」を計上するため、作業船の中では計上しない固定としてください。% ** *積算の整合性* ： 積算要領では、想定する工種に含まれる「作業船の単価表」へ損料を追加するとされており、テストもその船で行うのが標準的な考え方となります 。 そのため「 *非航旋回* 」で計上します。 %{color:red}※実際に親となる捨て石基礎均しやブロック据え付け で使用する船なので旋回のほうを使用する% * …(続きはチケット参照) | J896: 新規歩掛 / 計上方法変更 | K896: 全パターン型 | L896: NEW(未カバードメイン) | M896: Closed | N896: Closed(要確認) | O896: 修正内容記載チケット | P896: 2 | Q896: 新ドメイン(65-3)。Verified豊富(運転費系除外)
A897: ◎ | C897: 604350 | D897: 65-3-32-26613 | G897: 港湾 | H897: 65-3-32-26613 港湾 (令和7年度(2025年度)) - ﾄﾗﾝｽﾎﾟﾝﾀﾞ撤去【新規追加】 #604351完了後 | I897: h4. *■資料■* ICT を活用した工事安全対策試行工事（潜水作業） 積算要領（令和７年度） (001880123).pdf 新規作成 h4. *■外部設計■* ##604351 と同じ ※潜水士船について 「艤装テスト」は潜水を伴う本格稼働なので、潜水班込みの『運転』。 「撤去」は船を足場として使うだけの機材回収なので、船体のみの『供用』＋必要な作業員（溶接工等）の積み上げ h4. *■内部設計■* 65-3-32-26612：ﾄﾗﾝｽﾎﾟﾝﾀﾞ艤装ﾃｽﾄ をリネームして値を変更 測量技師補を計上 潜水士船 供用 [65-3-32-20470] に潜水士船を変更 h4. *■テストケース■* 65-3-32-26612：ﾄﾗﾝｽﾎﾟﾝﾀﾞ艤装ﾃｽﾄ と比較して「内部設計」以外の変更がない | J897: 新規歩掛 | K897: 全パターン型 | L897: NEW(未カバードメイン) | M897: Closed | N897: Closed(要確認) | O897: 修正内容記載チケット | P897: 2 | Q897: 新ドメイン(65-3)。Verified豊富(運転費系除外)
A898: ◎ | C898: 617251 | D898: 65-34-32-1567 | G898: 維持修繕 | H898: 65-34-32-1567 路面清掃車による清掃 【資料以外】※1人テスト | I898: h4. 修正内容 資料の変更なし 旧損料:6-0-32-1792 を [6-0-33-5614]に繋ぎ変えしてください h4. テストケース 「代価表当り単位の選択」【】どちらも実行 <期待結果> 路面清掃車は、繋ぎ変え後の損料が計上される 変数Nhの値は繋ぎ変え後損料の値から計算した結果となっている その他は商品と一致する | J898: 単位変更 / 単価繋ぎ変え | K898: 差分型(要旧版確認) | L898: NEW(未カバードメイン) | M898: Closed | N898: Closed(要確認) | O898: 修正内容記載チケット | P898: 1 | Q898: 新ドメイン(65-34)
A899: ◎ | C899: 615583 | D899: 65-34-32-1712 | G899: 維持修繕 | H899: 65-34-32-1712 支障木の伐根※1人修正1人テスト | I899: h4. ■資料 02273.addlayerol.pdf P143/446 h4. ■修正方針 * 代価表 ** 7行目 *** 資料通りの損料へ繋ぎ替え * 質問 ** 質問No10 *** 削除 * フロー ** 上記質問削除に伴い修正 h4. ■テストケース * 積算実行 * 期待結果 ** 資料通りの規格でﾁｪｰﾝｿｰが計上される ** 上記以外は商品と一致する | J899: 質問追加/削除 | K899: 差分型(要旧版確認) | L899: NEW(未カバードメイン) | M899: Closed | N899: Closed(要確認) | O899: 修正内容記載チケット | P899: 2 | Q899: 新ドメイン(65-34)
A900: ◎ | C900: 615805 | D900: 65-34-32-1727 | G900: 維持修繕 | H900: 65-34-32-1727 伐根･除根※1人修正1人テスト | I900: h4. ■資料 02273.addlayerol.pdf P257/466 h4. ■修正方針 * 質問 ** 質問No11 *** 資料通りにデフォルト設定 h4. ■テストケース * 積算実行 * 期待結果 ** 不整地運搬車は資料通りの排ガス規格がデフォルトで計上される ** 上記以外は商品と一致する | J900: 初期値 | K900: 差分型(要旧版確認) | L900: NEW(未カバードメイン) | M900: Closed | N900: Closed(要確認) | O900: 修正内容記載チケット | P900: 2 | Q900: 新ドメイン(65-34)
A901: ◎ | C901: 615835 | D901: 65-34-32-1782 | G901: 維持修繕 | H901: 【詳細設計】65-34-32-1782 地力回復(土地改良材散布) | I901: h2. ##615573 上記チケットより、文字変更の範囲外と判断して詳細設計作成 資料P 354/466 名称変更（「土地改良～」⇒「土壌改良～」） 変数指定HM＝1によって代価表名称が「土地改良～」となるようにしているようです （実体側ではHM＝1のとき、「土地改良～」、HM＝0のとき「土壌改良～」としている） ⇒変数指定の修正や、変数HMの要不要について、ご判断お願いいたします h2. 設計者 ** 修正内容：実装チケットに記載。 ** 予定工数：実際にかかりそうな時間を入力。 ** タイトル *** 全国工種を修正する場合は地域に合わせて年度毎のチケットが揃っているか確認 *** 【XML】65-xx-xx-xxxxx / 65-xxxx-xx-xxxxx 省庁名 (令和xx年度) - 工種名 _ 修正内容 / ★SC (65-xx-xx-xxxxx) #○○完了後 着手順① *** 【エクセル等】【工種リスト】 省庁名 (令和XX年度) - 工種名 [65-X-32-XXXXX] 計●工種 _ 修正内容 ★～注意事項～ #○○完了後 着手順① ** テストケース：Excelへ記載。 ** ステータス：詳細設計が完了したら、詳細設計タスク・実装タスクを「テストケースレビュー待ち」にしてください --- h2. レビュー者 ** 修 …(続きはチケット参照) | J901: 文字修正 / 子代価/SC | K901: 差分型(要旧版確認) | L901: NEW(未カバードメイン) | M901: Closed | N901: Closed(要確認) | O901: 設計系のみ(修正方針は関連チケット参照) | P901: 1 | Q901: 新ドメイン(65-34)
A902: ◎ | C902: 615837 | D902: 65-34-32-465 | G902: 維持修繕 | H902: ※別チケットにてまとめて対応のためClose【詳細設計】65-34-32-465 ①放射線の事前測定 | I902: h2. ##615573 上記チケットより、文字変更の範囲外と判断して詳細設計作成 資料P 401/466 名称変更（「放射線の事前測定」⇒「放射線の事前測定点設置作業」） 変数指定HM＝2によって代価表名称が「放射線の事前測定」となるようにしているようです （実体側ではHM＝2のとき、「放射線の事前測定」、HM＝0のとき「放射線の事前測定点設置作業」としている） ⇒変数指定の修正が必要かと思います。ご判断お願い致します h2. 設計者 ** 修正内容：実装チケットに記載。 ** 予定工数：実際にかかりそうな時間を入力。 ** タイトル *** 全国工種を修正する場合は地域に合わせて年度毎のチケットが揃っているか確認 *** 【XML】65-xx-xx-xxxxx / 65-xxxx-xx-xxxxx 省庁名 (令和xx年度) - 工種名 _ 修正内容 / ★SC (65-xx-xx-xxxxx) #○○完了後 着手順① *** 【エクセル等】【工種リスト】 省庁名 (令和XX年度) - 工種名 [65-X-32-XXXXX] 計●工種 _ 修正内容 ★～注意事項～ #○○完了後 着手順① ** テストケース：Excelへ記載。 ** ステータス：詳細設計が完了したら、詳細設計タスク・実装タスクを「テストケースレビュー待ち」にしてください --- …(続きはチケット参照) | J902: 文字修正 / 子代価/SC | K902: 差分型(要旧版確認) | L902: NEW(未カバードメイン) | M902: Closed | N902: Closed(要確認) | O902: 設計系のみ(修正方針は関連チケット参照) | P902: 1 | Q902: 新ドメイン(65-34)
A903: ◎ | C903: 613994 | D903: 65-2-32-22961 | G903: 農林 | H903: 65-2-32-22961 不整地運搬 ※#613999対応後 | I903: h4. ■資料 【標準歩掛】3/162 h4. ■変更内容 運転費指定事項、排ガス変更 h4. ■詳細設計メモ https://dev-redmine.being.group/issues/612689#note-8 h4. ■修正方針 * 質問No.2 ** 排ｶﾞｽ対策型(第1次基準値) ⇒ 排ｶﾞｽ対策型(2011年規制) に文字修正する * フロー ** X:5･Y:2のフローコマンドの値を15に修正する * ※「サブルーチン排ガス質問を用意する」が正しいが、サブルーチン [65-2000-8193-141]に積載質量8.0～11.0t積用が存在しないため、作成する必要があり工数がかかる 上記の理由でこの修正方針にしています。 h4. ■テストケース * 積算実行する ** 排ガスの質問は、資料通り「排ｶﾞｽ対策2011年規制」が初期位置で開く ** 運転費内で開いてくる質問はなく、代価表に計上される軽油の数量、運転費規格は資料通りになる | J903: 文字修正 / 子代価/SC | K903: 差分型(要旧版確認) | L903: NEW(未カバードメイン) | M903: Verified | N903: Verified(資料・データ確実) | O903: 修正内容記載チケット | P903: 2 | Q903: 新ドメイン(65-2)
A904: ◎ | C904: 613236 | D904: 65-2-32-22991 | G904: 農林 | H904: 65-2-32-22991 / 65-4002-50-20508 機械小運搬(土砂類､生ｺﾝ)､機械小運搬(二次製品､管類､ｾﾒﾝﾄ類) | I904: h4. ■資料 【標準歩掛】5～6/162 h4. ■変更内容 排ガス変更 h4. ■修正方針 * 質問No12 ** 初期値を「第2次基準値」 ** 「(※標準)」の文言を1次から2次 * 「サブルーチン排ガス質問を用意する」が正しいが、 変数名が変わってしまう＝システムテストが必要＝工数かかる 以上の理由でこの修正方針にします。 h4. ■テストケース 単体テストのみ | J904: 子代価/SC / 初期値 | K904: 差分型(要旧版確認) | L904: NEW(未カバードメイン) | M904: Verified | N904: Verified(資料・データ確実) | O904: 修正内容記載チケット | P904: 2 | Q904: 新ドメイン(65-2)
A905: ◎ | C905: 612762 | D905: 65-2-32-23089 | G905: 農林 | H905: 65-2-32-23089 / 65-4002-50-22242 やぐら設置･撤去工 ﾀﾞｳﾝｻﾞﾎｰﾙﾊﾝﾏ工【基礎工】 / ★SC(65-2-32-25537) ※テストのみ実行 | I905: h4. 資料 * 【標準歩掛】 P22,24～39/162 h4. 修正方針 * テストのみ実行する h4. テストケース 以下のテストを実行する 操作：積算を実行する 期待結果： * 索道の動作が削除されている * それ以外の動作･結果は商品で「ﾗﾌﾃﾚｰﾝｸﾚｰﾝ使用」を選択した時と一致する | J905: 子代価/SC | K905: 差分型(要旧版確認) | L905: NEW(未カバードメイン) | M905: Verified | N905: Verified(資料・データ確実) | O905: 修正内容記載チケット | P905: 2 | Q905: 新ドメイン(65-2)
A906: ◎ | C906: 613868 | D906: 65-2-32-23163 | G906: 農林 | H906: 65-2-32-23163 ﾊﾟｲﾌﾟﾗｲﾝ基礎【管水路工】 / ★SC(65-2-32-25675) #613988 完了後 | I906: h4. 資料 * 【標準歩掛】58～60/162 h4. 資料変更内容 * ﾊﾞｯｸﾎｳ計上追加 h4. 修正方針 ﾊﾞｯｸﾎｳ計上追加 ⇒排ガス変更(賃料のため排ガス変更は影響なし)、燃料消費量変更 * #613988 完了後にテストのみ実行する h4. テストケース * システムテスト ** 操作 「ﾊﾞｯｸﾎｳ規格選択」【山積0.45m3(平積0.35m3),山積0.80m3(平積0.60m3)】 ** 期待結果 子代価のﾊﾞｯｸﾎｳは燃料消費量が資料通りの値で計上される 上記以外の動作、結果は商品と一致する | J906: 子代価/SC | K906: 差分型(要旧版確認) | L906: NEW(未カバードメイン) | M906: Verified | N906: Verified(資料・データ確実) | O906: 修正内容記載チケット | P906: 2 | Q906: 新ドメイン(65-2)
... A964: ◎ | C964: 612894 | D964: 65-28-32-30 | G964: 電気通信 | H964: 65-28-32-30 ﾊﾞｯｸﾎｳ積込 | I964: +*■資料*+ \\being.group\Being-限定共有\積算基準\28ダム\○01国交省・ダム工事積算\2026(R8)\令和７年度改定箇所（令和８年４月１日以降適用） (001982681).pdf 新旧表 5~13/39 +*■変更点*+ 山積･平積→バケット容量 +*■修正内容*+ ・「山積」を「ﾊﾞｹｯﾄ容量」に置換 ・質問No3 メモ先頭のﾊﾞｹｯﾄ容量だけ残して2つ目以降は省略 ・平積は置換よりも使用箇所を検索して直していくのが良いかな（良きように！） +*■テスト*+ 単体テストのみでOK | J964: (個別確認) | K964: 差分型(要旧版確認) | L964: NEW(未カバードメイン) | M964: Closed | N964: Closed(要確認) | O964: 修正内容記載チケット | P964: 1 | Q964: 新ドメイン(65-28)

Sheet ドメイン別サマリ
A1: ドメイン | B1: 候補数 | C1: ★採用数 | D1: 備考
A2: NEXCO | B2: =COUNTIF(候補一覧!G2:G964,A2) -> 6 | C2: =COUNTIFS(候補一覧!G2:G964,A2,候補一覧!B2:B964,"★") -> 1 | D2: 新ドメイン(65-11)
A3: PC橋 | B3: =COUNTIF(候補一覧!G2:G964,A3) -> 35 | C3: =COUNTIFS(候補一覧!G2:G964,A3,候補一覧!B2:B964,"★") -> 3 | D3: 新ドメイン(65-4)
A4: トンネル | B4: =COUNTIF(候補一覧!G2:G964,A4) -> 26 | C4: =COUNTIFS(候補一覧!G2:G964,A4,候補一覧!B2:B964,"★") -> 2 | D4: 新ドメイン(65-6)
A5: 一般土木 | B5: =COUNTIF(候補一覧!G2:G964,A5) -> 584 | C5: =COUNTIFS(候補一覧!G2:G964,A5,候補一覧!B2:B964,"★") -> 4 | D5: 既存カバー領域の精度確認用
A6: 上水道 | B6: =COUNTIF(候補一覧!G2:G964,A6) -> 21 | C6: =COUNTIFS(候補一覧!G2:G964,A6,候補一覧!B2:B964,"★") -> 2 | D6: 新ドメイン(65-9)
A7: 下水維持 | B7: =COUNTIF(候補一覧!G2:G964,A7) -> 3 | C7: =COUNTIFS(候補一覧!G2:G964,A7,候補一覧!B2:B964,"★") -> 1 | D7: 新ドメイン(65-29)
A8: 下水道 | B8: =COUNTIF(候補一覧!G2:G964,A8) -> 9 | C8: =COUNTIFS(候補一覧!G2:G964,A8,候補一覧!B2:B964,"★") -> 1 | D8: 新ドメイン(65-22)
A9: 共通仮設 | B9: =COUNTIF(候補一覧!G2:G964,A9) -> 5 | C9: =COUNTIFS(候補一覧!G2:G964,A9,候補一覧!B2:B964,"★") -> 1 | D9: 新ドメイン(65-5)
A10: 建築歩掛 | B10: =COUNTIF(候補一覧!G2:G964,A10) -> 1 | C10: =COUNTIFS(候補一覧!G2:G964,A10,候補一覧!B2:B964,"★") -> 1 | D10: 新ドメイン(65-31)
A11: 機器費 | B11: =COUNTIF(候補一覧!G2:G964,A11) -> 3 | C11: =COUNTIFS(候補一覧!G2:G964,A11,候補一覧!B2:B964,"★") -> 1 | D11: 新ドメイン(65-24)
A12: 機械設備 | B12: =COUNTIF(候補一覧!G2:G964,A12) -> 3 | C12: =COUNTIFS(候補一覧!G2:G964,A12,候補一覧!B2:B964,"★") -> 1 | D12: 新ドメイン(65-21)
A13: 治山林道 | B13: =COUNTIF(候補一覧!G2:G964,A13) -> 8 | C13: =COUNTIFS(候補一覧!G2:G964,A13,候補一覧!B2:B964,"★") -> 2 | D13: 新ドメイン(65-23)
A14: 測量(UAV等) | B14: =COUNTIF(候補一覧!G2:G964,A14) -> 1 | C14: =COUNTIFS(候補一覧!G2:G964,A14,候補一覧!B2:B964,"★") -> 1 | D14: 新ドメイン(65-32)
A15: 港湾 | B15: =COUNTIF(候補一覧!G2:G964,A15) -> 169 | C15: =COUNTIFS(候補一覧!G2:G964,A15,候補一覧!B2:B964,"★") -> 4 | D15: 新ドメイン(65-3)。Verified豊富(運転費系除外)
A16: 空港 | B16: =COUNTIF(候補一覧!G2:G964,A16) -> 3 | C16: =COUNTIFS(候補一覧!G2:G964,A16,候補一覧!B2:B964,"★") -> 2 | D16: 新ドメイン(65-25)
A17: 維持修繕 | B17: =COUNTIF(候補一覧!G2:G964,A17) -> 6 | C17: =COUNTIFS(候補一覧!G2:G964,A17,候補一覧!B2:B964,"★") -> 1 | D17: 新ドメイン(65-34)
A18: 農林 | B18: =COUNTIF(候補一覧!G2:G964,A18) -> 63 | C18: =COUNTIFS(候補一覧!G2:G964,A18,候補一覧!B2:B964,"★") -> 4 | D18: 新ドメイン(65-2)
A19: 鉄道 | B19: =COUNTIF(候補一覧!G2:G964,A19) -> 1 | C19: =COUNTIFS(候補一覧!G2:G964,A19,候補一覧!B2:B964,"★") -> 1 | D19: 新ドメイン(65-27)
A20: 防衛省 | B20: =COUNTIF(候補一覧!G2:G964,A20) -> 1 | C20: =COUNTIFS(候補一覧!G2:G964,A20,候補一覧!B2:B964,"★") -> 1 | D20: 新ドメイン(65-30)
A21: 電気通信 | B21: =COUNTIF(候補一覧!G2:G964,A21) -> 15 | C21: =COUNTIFS(候補一覧!G2:G964,A21,候補一覧!B2:B964,"★") -> 2 | D21: 新ドメイン(65-28)
A22: 合計 | B22: =SUM(B2:B21) -> 963 | C22: =SUM(C2:C21) -> 36 | D22: 既存22＋★で50超

Sheet 凡例・選定方針
A1: 項目 | B1: 説明
A2: チケット# | B2: 工種ごとに1チケットに厳選。設計系(詳細設計/再設計/追加設計)を除外し、Verified優先・説明欄が充実したものを代表に採用
A3: 説明(修正方針の記載元) | B3: 代表チケットの説明欄(先頭600字)。修正方針.txt の元ネタ。設計系しか無い工種は「チケット種別」列で明示
A4: 推奨度 | B4: ◎=未カバードメイン / ○=既存カバー(精度確認用) / △=制限事項(損料・賃料・〜運転・機械経費系)
A5: 採用推奨★ | B5: 説明欄あり>Verified>関連件数 の順で優先選定
A6: 選定方針 | B6: ①新パターン優先(未カバー20ドメイン) ②既網羅の精度確認(一般土木4) ③制限事項は△除外 ④既存22工種・対応不要は除外
A7: 元データ | B7: docs/260612_Gaiaデータ_issues_export.xls → 工種ID付き → ユニーク950工種
